setup.py
kombu/__init__.py
kombu/abstract.py
kombu/compat.py
kombu/compression.py
kombu/connection.py
kombu/entity.py
kombu/exceptions.py
kombu/messaging.py
kombu/pidbox.py
kombu/serialization.py
kombu/simple.py
kombu/syn.py
kombu/tests/__init__.py
kombu/tests/mocks.py
kombu/tests/test_compat.py
kombu/tests/test_compression.py
kombu/tests/test_connection.py
kombu/tests/test_entities.py
kombu/tests/test_messaging.py
kombu/tests/test_pidbox.py
kombu/tests/test_serialization.py
kombu/tests/test_simple.py
kombu/tests/test_transport.py
kombu/tests/test_transport_base.py
kombu/tests/test_transport_memory.py
kombu/tests/test_transport_pyamqplib.py
kombu/tests/test_transport_pyredis.py
kombu/tests/test_transport_virtual.py
kombu/tests/test_utils.py
kombu/tests/test_virtual_exchange.py
kombu/tests/test_virtual_scheduling.py
kombu/tests/utils.py
kombu/transport/__init__.py
kombu/transport/base.py
kombu/transport/beanstalk.py
kombu/transport/librabbitmq.py
kombu/transport/memory.py
kombu/transport/mongodb.py
kombu/transport/pyamqplib.py
kombu/transport/pycouchdb.py
kombu/transport/pypika.py
kombu/transport/pyredis.py
kombu/transport/virtual/__init__.py
kombu/transport/virtual/exchange.py
kombu/transport/virtual/scheduling.py
kombu/utils/__init__.py
kombu/utils/compat.py
kombu/utils/eventio.py
kombu/utils/finalize.py
kombu/utils/functional.py
scuttle/__init__.py
scuttle/parselog.py
scuttle/process.py
scuttle/version.py
scuttle.egg-info/PKG-INFO
scuttle.egg-info/SOURCES.txt
scuttle.egg-info/dependency_links.txt
scuttle.egg-info/top_level.txt
scuttle/loggers/__init__.py
scuttle/loggers/file.py
scuttle/loggers/gearman.py
scuttle/loggers/kombulogger.py
scuttle/parsers/__init__.py
scuttle/parsers/accesslog.py
scuttle/utils/__init__.py