Metadata-Version: 1.0
Name: scuttle
Version: 0.4
Summary: Scuttle is an analytics logging library
Home-page: http://samuelks.com/scuttle/
Author: Samuel Stauffer
Author-email: samuel@descolada.com
License: UNKNOWN
Platform: UNKNOWN
Classifier: Intended Audience :: Developers
Classifier: License :: OSI Approved :: BSD License
Classifier: Operating System :: OS Independent
Classifier: Programming Language :: Python
Classifier: Topic :: Software Development :: Libraries :: Python Modules
